compsheet
