Metadata-Version: 2.1
Name: compsheet
Version: 1.0.6
Summary: compare microsoft spreadsheet data to check for plagiarism
Home-page: https://github.com/dfujim/SpreadsheetPlagiarism
Author: Derek Fujimoto
Author-email: fujimoto@phas.ubc.ca
License: UNKNOWN
Platform: UNKNOWN
Classifier: Programming Language :: Python :: 3
Classifier: License :: OSI Approved :: MIT License
